seqm/__init__.py
seqm/__main__.py
seqm/__utils__.py
seqm/conversion.py
seqm/distance.py
seqm/metrics.py
seqm/objects.py
seqm/utils.py
seqm/bin/Darwin/oligotm
seqm/bin/Linux/oligotm
seqm-0.1.0.dist-info/LICENSE
seqm-0.1.0.dist-info/METADATA
seqm-0.1.0.dist-info/WHEEL
seqm-0.1.0.dist-info/entry_points.txt
seqm-0.1.0.dist-info/top_level.txt
seqm-0.1.0.dist-info/RECORD
