Metadata-Version: 2.1
Name: seqm
Version: 0.1.0
Summary: Utilities for calculating sequence metrics.
Home-page: https://github.com/atgtag/seqm
Author: Blake Printy
Author-email: bprinty@gmail.com
License: MIT
Keywords: seqm,seq,sequence,metrics,ngs,sequencing,distance,hamming,edit
Platform: UNKNOWN
Classifier: Intended Audience :: Developers
Classifier: License :: OSI Approved :: Apple Public Source License
Classifier: Natural Language :: English
Classifier: Programming Language :: Python :: 2
Classifier: Programming Language :: Python :: 2.6
Classifier: Programming Language :: Python :: 2.7
Classifier: Programming Language :: Python :: 3
Classifier: Programming Language :: Python :: 3.3
Classifier: Programming Language :: Python :: 3.4
Classifier: Programming Language :: Python :: 3.5
Classifier: Programming Language :: Python :: 3.6
Classifier: Programming Language :: Python :: 3.7
Requires-Dist: cached-property (>=1.2.0)
Requires-Dist: editdistance (>=0.3.1)
